Workbook

Sheet Sheet1
A3: Row Labels
A4: 3. Order Entry / Completion
A5: 4. Rx Setup
A6: 5. Claims to Adjudicate - New Rx's
A7: 6. Benefits Verification - New Rx's
A8: 7. Rx Verification
A9: 9. Patients to Contact - Refills
A10: A. Patients to Contact - New Rx's
A11: B. Patients to Contact - Refills
A12: C. Claims to Adjudicate - Refills
A13: E. Print Labels / Documentation
A14: F. Select Lots / Fill Rx
... A17: Grand Total

Sheet Order Last Event Mapping
A1: Order Last Event | B1: Queue | C1: Order Last Event Status | D1: Anovo DB (Order Last Event Status) | E1: Dashboard Status | F1: Status Type | G1: other | H1: SF | I1: roll exhaust
A2: 1st eRx Attempt | B2: B. Patients to Contact - Refills | C2: Patients to Contact - Scheduling Shipment | D2: Patients to Contact - Scheduling Shipment | F2: Active | G2: Utilize if 1st erx attempt is made to obtain new prescription while in queue B | J2: All
A3: 1st eRx Attempt | B3: I. Rx Expiration / Zero Refills | C3: New Rx Needed - 1st eRx Attempt | D3: New Rx Needed - 1st eRx Attempt | F3: Active | G3: Utilize for 1st attempt to obtain eRx Day 1 | H3: X | J3: All | K3: do we want attempts on external?
A4: 1st Fax Attempt | B4: B. Patients to Contact - Refills | C4: Patients to Contact - Scheduling Shipment | D4: Patients to Contact - Scheduling Shipment | F4: Active | G4: Utilize if 1st fax attempt is made to obtain new prescription while in queue B | J4: All
A5: 1st Fax Attempt | B5: C. Claims to Adjudicate - Refills | C5: Shipment Scheduled | D5: Shipment Scheduled | F5: Active | G5: Utilize if 1st fax attempt is sent for new prescription and patient has shipment scheduled | J5: All
A6: 1st Fax Attempt | B6: I. Rx Expiration / Zero Refills | C6: New Rx Needed - 1st Fax Attempt | D6: New Rx Needed - 1st Fax Attempt | F6: Active | G6: Utilize for 1st fax attempt to obtain new Rx Day 1 | H6: X | J6: All
A7: 1st Scheduling Attempt | B7: A. Patients to Contact - New Rx's | C7: Patients to Contact - Scheduling Shipment: 1st Attempt | D7: Patients to Contact - Scheduling Shipment: 1st Attempt | F7: Pending | G7: Utilize if 1st scheduling attempt has been made for new patient | J7: All
A8: 1st Scheduling Attempt | B8: B. Patients to Contact - Refills | C8: Patients to Contact - Scheduling Shipment: 1st Attempt | D8: Patients to Contact - Scheduling Shipment: 1st Attempt | F8: Active | G8: Utilize if 1st scheduling attempt has been made for refill | J8: All
A9: 2nd eRx Attempt | B9: B. Patients to Contact - Refills | C9: Patients to Contact - Scheduling Shipment | D9: Patients to Contact - Scheduling Shipment | F9: Active | G9: Utilize if 2nd erx attempt is made to obtain new prescription while in queue B | J9: All
A10: 2nd eRx Attempt | B10: I. Rx Expiration / Zero Refills | C10: New Rx Needed - 2nd eRx Attempt | D10: New Rx Needed - 2nd eRx Attempt | F10: Active | G10: Utilize for 2nd attempt to obtain eRx | H10: X | J10: All | K10: do we want attempts on external?
A11: 2nd Fax Attempt | B11: B. Patients to Contact - Refills | C11: Patients to Contact - Scheduling Shipment | D11: Patients to Contact - Scheduling Shipment | F11: Active | G11: Utilize if 2nd fax attempt is made to obtain new prescription while in queue B | J11: All
A12: 2nd Fax Attempt | B12: I. Rx Expiration / Zero Refills | C12: New Rx Needed - 2nd Fax Attempt | D12: New Rx Needed - 2nd Fax Attempt | F12: Active | G12: Utilize for 2nd fax attempt to obtain new Rx Day 4 | H12: X | J12: All
A13: 2nd Scheduling Attempt | B13: A. Patients to Contact - New Rx's | C13: Patients to Contact - Scheduling Shipment: 2nd Attempt | D13: Patients to Contact - Scheduling Shipment: 2nd Attempt | F13: Pending | G13: Utilize if 2nd scheduling attempt has been made for new patient | J13: All
A14: 2nd Scheduling Attempt | B14: B. Patients to Contact - Refills | C14: Patients to Contact - Scheduling Shipment: 2nd Attempt | D14: Patients to Contact - Scheduling Shipment: 2nd Attempt | F14: Active | G14: Utilize if 2nd scheduling attempt has been made for refill | J14: All
A15: 3rd Scheduling Attempt | B15: A. Patients to Contact - New Rx's | C15: Patients to Contact - Scheduling Shipment: 3rd Attempt | D15: Patients to Contact - Scheduling Shipment: 3rd Attempt | F15: Pending | G15: Utilize if 3rd scheduling attempt has been made for new patient | J15: All
A16: 3rd Scheduling Attempt | B16: B. Patients to Contact - Refills | C16: Patients to Contact - Scheduling Shipment: 3rd Attempt | D16: Patients to Contact - Scheduling Shipment: 3rd Attempt | F16: Active | G16: Utilize if 3rd Scheduling attempt has been made for refill | J16: All
A17: 4th Scheduling Attempt | B17: A. Patients to Contact - New Rx's | C17: Patients to Contact - Scheduling Shipment: 4th Attempt | D17: Patients to Contact - Scheduling Shipment: 4th Attempt | F17: Pending | G17: Utilize if 4th scheduling attempt has been made for new patient ( WHEN MOVING ORDER FROM QUEUE A TO B, THE STATUS SHOULD CONTINUE TO PATIENT TO CONTACT: SCHEDULING SHIPMENT:5TH ATTEMPT IF 4TH ATTEMPT IS UNSUCESSFUL) | J17: All
A18: 4th Scheduling Attempt | B18: B. Patients to Contact - Refills | C18: Patients to Contact - Scheduling Shipment: 4th Attempt | D18: Patients to Contact - Scheduling Shipment: 4th Attempt | F18: Pending | G18: Utilize if 4th scheduling attempt has been made for refill | J18: All
A19: 4th Scheduling Attempt | B19: B. Patients to Contact - Refills | C19: Patients to Contact - Scheduling Shipment: 4th Attempt | D19: Patients to Contact - Scheduling Shipment: 4th Attempt | F19: Active | G19: Utilize if 4th scheduling attempt has been made for refill | J19: All
A20: 5th Scheduling Attempt | B20: B. Patients to Contact - Refills | C20: Patients to Contact - Scheduling Shipment: 5th Attempt | D20: Patients to Contact - Scheduling Shipment: 5th Attempt | F20: Active | G20: Utilize if 5th scheduling attempt has been made for refill | J20: All
A21: 6th Scheduling Attempt | B21: B. Patients to Contact - Refills | C21: Patients to Contact - Scheduling Shipment: 6th Attempt | D21: Patients to Contact - Scheduling Shipment: 6th Attempt | F21: Active | G21: Utilize if 6th scheduling attempt has been made for refill | J21: All
A22: Call to schedule | B22: B. Patients to Contact - Refills | C22: Patients to Contact - Scheduling Shipment | D22: Patients to Contact - Scheduling Shipment | F22: Active | G22: Utilize if pharmacist wants outreach made to specific patient - probably do not call patients
A23: Called and left message with MDO rep | B23: 4. Rx Setup | C23: Rx Clarification Needed | D23: Called MDO for Rx clarification | F23: Pending | G23: Utilize if clarification needed, called MDO and left message with representative | H23: x (possibly) | J23: All
A24: Called and left message with MDO rep | B24: 7. Rx Verification | C24: Rx Verification | D24: Rx Verification | F24: Pending | G24: Utilized when a pharmacist needs verification and has called the MDO to obtain what is needed | J24: All
A25: Called and left Voicemail | B25: 4. Rx Setup | C25: Rx Clarification Needed | D25: Called MDO for Rx clarification | F25: Pending | G25: Utilize if clarification needed, called MDO and left voicemail | H25: x (possibly) | J25: All
A26: Called and left Voicemail | B26: I. Rx Expiration / Zero Refills | C26: New Rx Needed | D26: New Rx Needed | F26: Active | G26: Utilize if left VM with MD while trying to obtain new Rx | H26: X | J26: All
A27: Clarification Needed | B27: 4. Rx Setup | C27: Rx Clarification Needed | D27: Clarification Needed | F27: Pending | G27: Utilize if clarification needed, office is closed | H27: x (possibly) | J27: All
A28: Clarification Needed | B28: 7. Rx Verification | C28: Rx Clarification Needed | D28: Clarification Needed | F28: Pending | G28: Utilized when a pharmacist needs verification and has called the MDO to obtain what is needed
A29: Discontinue Rx | B29: 4. Rx Setup | C29: Rx Clarification Needed | D29: Rx Clarification Needed | F29: Pending | G29: Utilize if pharmacist needs to discontinue Rx due to annotation scanned back in | J29: All
A30: Discontinue Rx | B30: I. Rx Expiration / Zero Refills | F30: Active | G30: Utilize if pharmacist needs to dc previous prescription | J30: All | K30: pull status from the other Rx
A31: Drug on Hand - Dose Decrease | B31: B. Patients to Contact - Refills | C31: Drug on Hand - Dose Decrease | D31: Drug on Hand - Dose Decrease | F31: Active | G31: Utilize if patient has doh due to dose decrease | I31: Y | J31: All
A32: Drug on Hand - Dose Increase | B32: B. Patients to Contact - Refills | C32: Drug on Hand - Dose Increase | D32: Drug on Hand - Dose Increase | F32: Active | I32: Y
A33: Drug on Hand - Drug on Hold | B33: B. Patients to Contact - Refills | C33: Drug on Hand - Therapy on Hold | D33: Drug on Hand - Therapy on Hold | F33: Active | G33: Utilize for any other reason to hold therapy MD or Patient | I33: Y | J33: All
A34: Drug on Hand - Lab/ Testing | B34: B. Patients to Contact - Refills | C34: Drug on Hand - Lab/Testing | D34: Drug on Hand - Lab/Testing | F34: Active | I34: Y
A35: Drug on Hand - Medical Reason | B35: B. Patients to Contact - Refills | C35: Drug on Hand - Medical Reason | D35: Drug on Hand - Medical Reason | F35: Active | I35: Y
A36: Drug on Hand - Other | B36: B. Patients to Contact - Refills | C36: Drug on Hand - Other | D36: Drug on Hand - Other | F36: Active | I36: Y
A37: Drug on Hand - Patient Non-Compliant | B37: B. Patients to Contact - Refills | C37: Drug on Hand - Patient Non-Compliant | D37: Drug on Hand - Patient Non-Compliant | F37: Active | I37: Y
A38: Drug on Hand - Side Effects | B38: B. Patients to Contact - Refills | C38: Drug on Hand- Side Effects | D38: Drug on Hand- Side Effects | F38: Active | G38: Utilize if patient has DOH due to experiencing side effects | I38: Y
A39: Drug on Hand - Slow Titration | B39: B. Patients to Contact - Refills | C39: Drug on Hand - Slow Titration | D39: Drug on Hand - Slow Titration | F39: Active | G39: Utilize if patient is slow to titrate and has drug on hand | I39: Y | J39: Fintepla, Firdapse, Isturisa
A40: Drug on Hand - Tapering Off | B40: B. Patients to Contact - Refills | C40: Drug on Hand - Tapering Off Drug | D40: Drug on Hand - Tapering Off Drug | F40: Active | G40: Utilize if patient is tapering off medication | I40: Y | J40: Fintepla
A41: Duplicate Rx - Discontinue | B41: 3. Order Entry / Completion | F41: Pending
A42: Duplicate Rx - Discontinue | B42: 4. Rx Setup | F42: Active
A43: Duplicate Rx - Discontinue | B43: 5. Claims to Adjudicate - New Rx's | F43: Pending
A44: Duplicate Rx - Discontinue | B44: 6. Benefits Verification - New Rx's | F44: Pending
A45: Duplicate Rx - Discontinue | B45: 7. Rx Verification | F45: Active
A46: Duplicate Rx - Discontinue | B46: 9. Patients to Contact - Refills | F46: Active
A47: Duplicate Rx - Discontinue | B47: A. Patients to Contact - New Rx's | F47: Pending
A48: Duplicate Rx - Discontinue | B48: B. Patients to Contact - Refills | F48: Active
A49: Duplicate Rx - Discontinue | B49: C. Claims to Adjudicate - Refills | F49: Active
A50: Duplicate Rx - Discontinue | B50: D. Benefits Verification - Refills | F50: Active
A51: Duplicate Rx - Discontinue | B51: E. Print Labels / Documentation | F51: Active
A52: Duplicate Rx - Discontinue | B52: F. Select Lots / Fill Rx | F52: Active
A53: Duplicate Rx - Discontinue | B53: I. Rx Expiration / Zero Refills | F53: Active
A54: Has another Rx as well | B54: 4. Rx Setup | C54: Rx Clarification Needed | D54: Clarification Needed | F54: Pending | G54: Utilize if patient has Rx set to ship (same dose); hold in queue 4 until other Rx ships | K54: use last event from other open order
A55: Has another Rx as well | B55: C. Claims to Adjudicate - Refills | C55: Shipment Scheduled | D55: Shipment Scheduled | F55: Active | G55: Utilize if patient has shipment scheduled and another Rx | J55: All
A56: Hold Patient in Hospital | B56: B. Patients to Contact - Refills | C56: Drug on Hold- Patient Hospitalized | D56: Drug on Hold- Patient Hospitalized | F56: Active | G56: Utilize if patient is not scheduling shipment due to hospitalization | I56: Y
A57: Inconvenient Time for Call | B57: A. Patients to Contact - New Rx's | C57: Patients to Contact - Sched Ship Pt Req Call Back | D57: Patients to Contact - Sched Ship Pt Req Call Back | F57: Pending | G57: Utilize if selected in Therigy precall, ex: patient is driving, at MD, etc., pharmacy will call back | J57: All
A58: Inconvenient Time for Call | B58: B. Patients to Contact - Refills | C58: Patients to Contact - Sched Ship Pt Req Call Back | D58: Patients to Contact - Sched Ship Pt Req Call Back | F58: Active | G58: Utilize if selected in Therigy precall, ex: patient is driving, at MD, etc., pharmacy will call back | J58: All
A59: Intake: Alt Funding/Foundation in Process | B59: 3. Order Entry / Completion | C59: Intake: Patient Assistance in Process | D59: Intake: Alt Funding/Foundation in Process | F59: Pending | G59: Utilize when patient is trying to obtain additional funding | J59: All
A60: Intake: Appeal Add'l Info needed from HCP | B60: 3. Order Entry / Completion | C60: Intake: Appeal Add'l Info needed from HCP | D60: Intake: Appeal Add'l Info needed from HCP | F60: Pending | G60: Utilize if Insurance requests additional info from HCP for Appeal completion | J60: All
A61: Intake: Appeal Pending HCP Initial Submission | B61: 3. Order Entry / Completion | C61: Intake: Appeal Pending HCP Initial Submission | D61: Intake: Appeal Pending HCP Initial Submission | F61: Pending | G61: Utilize if HCP has not submitted Appeal to insurance and SF Assistance is needed | J61: All
A62: Intake: Appeal Pending Insurance Decision | B62: 3. Order Entry / Completion | C62: Intake: Appeal Pending Insurance Decision | D62: Intake: Appeal Pending Insurance Decision | F62: Pending | G62: Utilize if Appeal has been submitted to Insurance & waiting on decision | J62: All
A63: Intake: Appeal Required | B63: 3. Order Entry / Completion | C63: Intake: Appeal Required | D63: Intake: Appeal Required | F63: Pending | G63: Utilize when it is determined that a Appeal is required, but the Appeal has not been started | J63: All
A64: Intake: Benefits Discussion | B64: 3. Order Entry / Completion | C64: Intake: Contact Pt for Benefits Discussion | D64: Intake: Benefits Discussion | F64: Pending | G64: Attempting to complete Benefits Discussion | J64: All
A65: Intake: BV In Process | B65: 3. Order Entry / Completion | C65: Intake: BV In Process | D65: Intake: BV In Process | F65: Pending | G65: Utilize when BV is being completed | J65: All
A66: Intake: BV Needed | B66: 3. Order Entry / Completion | C66: Intake: BV In Process | D66: Intake: BV Needed | F66: Pending | G66: Utilize when it is identified that BV is needed but has not started yet | J66: All
A67: Intake: Contracting | B67: 3. Order Entry / Completion | C67: Pending Payer Contract | D67: Intake: Contracting | F67: Pending | G67: Utilize when contracting request is submitted | J67: All
A68: Intake: Indexing Complete | B68: 3. Order Entry / Completion | C68: Intake: BV In Process | D68: Intake: Indexing Complete | F68: Pending | G68: Utilize when referral data has been entered into the system and ready for BV
A69: Intake: Initiate PAP | B69: 3. Order Entry / Completion | C69: Intake: Initiate PAP | D69: Intake: Initiate PAP | F69: Pending | G69: Utilize if PAP screening and assessment are needed
A70: Intake: Missing Information from Prescriber | B70: 3. Order Entry / Completion | C70: Intake: Missing Information from Prescriber | D70: Intake: Missing Information from Prescriber | F70: Pending | G70: Utilize when information is needed from prescriber that cannot be obtained from the patient including referral is not clearly legible | J70: All
A71: Intake: Missing Insurance Info | B71: 3. Order Entry / Completion | C71: Intake: Missing Insurance Info | D71: Intake: Missing Insurance Info | F71: Pending | G71: Utilize when any insurance info is missing | J71: All
A72: Intake: New INS | B72: 3. Order Entry / Completion | C72: Intake: New Insurance Received | D72: Intake: New Insurance | F72: Pending | G72: Utilize when new insurance information is received after the BV/PA/Appeal process has started | J72: All
A73: Intake: On Hold Per Patient - Financial | B73: 3. Order Entry / Completion | C73: Intake: On Hold Per Patient - Financial | D73: Intake: On Hold Per Patient - Financial | F73: Pending | G73: Utilize if patient requests hold for financial reasons | I73: Y | J73: All
A74: Intake: On Hold Per Patient - MD Consult | B74: 3. Order Entry / Completion | C74: Intake: On Hold Per Patient - MD Consult | D74: Intake: On Hold Per Patient - MD Consult | F74: Pending | G74: Utilize if patient requests hold for MD appt, second opinion, lab tests, etc. | I74: Y | J74: All
A75: Intake: On Hold Per Patient - Other | B75: 3. Order Entry / Completion | C75: Intake: On Hold Per Patient - Other | D75: Intake: On Hold Per Patient - Other | F75: Pending | G75: Utilize if patients requests hold for any other reason | I75: Y | J75: All
A76: Intake: On Hold Per Prescriber - Lab/Testing | B76: 3. Order Entry / Completion | C76: Intake: On Hold Per Prescriber - Lab/Testing | D76: Intake: On Hold Per Prescriber - Lab/Testing | F76: Pending | G76: Utilize if HCP requests hold for lab tests | I76: Y | J76: All
A77: Intake: On Hold Per Prescriber - Lab/Testing | B77: 3. Order Entry / Completion | C77: Intake: On Hold Per Prescriber - Lab/Testing | D77: Intake: On Hold Per Prescriber - Lab/Testing | F77: Pending | I77: Y
A78: Intake: On Hold Per Prescriber - Other | B78: 3. Order Entry / Completion | C78: Intake: On Hold Per Prescriber - Other | D78: Intake: On Hold Per Prescriber - Other | F78: Pending | G78: Utilize if HCP requests hold for other reason | I78: Y | J78: All
A79: Intake: On Hold Per Prescriber - Surgery | B79: 3. Order Entry / Completion | C79: Intake: On Hold Per Prescriber - Surgery | D79: Intake: On Hold Per Prescriber - Surgery | F79: Pending | G79: Utilize if HCP requests hold for surgery | I79: Y | J79: All
A80: Intake: PA Add'l Info needed from HCP | B80: 3. Order Entry / Completion | C80: Intake: PA Add'l Info needed from HCP | D80: Intake: PA Add'l Info needed from HCP | F80: Pending | G80: Utilize if Insurance requests additional info from HCP for PA completion | J80: All
A81: Intake: PA Pending HCP Initial Submission | B81: 3. Order Entry / Completion | C81: Intake: PA Pending HCP Initial Submission | D81: Intake: PA Pending HCP Initial Submission | F81: Pending | G81: Utilize if HCP has not submitted PA to insurance | J81: All
A82: Intake: PA Pending Insurance Decision | B82: 3. Order Entry / Completion | C82: Intake: PA Pending Insurance Decision | D82: Intake: PA Pending Insurance Decision | F82: Pending | G82: Utilize if PA has been submitted to Insurance & waiting on decision | J82: All
A83: Intake: PA Required | B83: 3. Order Entry / Completion | C83: Intake: PA Required | D83: Intake: PA Required | F83: Pending | G83: Utilize when it is determined that a PA is required, but the PA has not been started | J83: All
A84: Intake: PAP Discussion | B84: 3. Order Entry / Completion | C84: Intake: Patient Notified of PAP Decision | D84: Intake: Patient Notified of PAP Decision | F84: Pending | G84: Utilize when notifying patient of PAP approval
A85: Intake: Pending Documents/Info from HUB | B85: 3. Order Entry / Completion | C85: Intake: Pending Documents/Info from HUB | D85: Intake: Pending Documents/Info from HUB | F85: Pending | G85: Utilize for Firdapse or Fintepla when complete documentation not received from Hub OR when Fintepla prescription received before the referral is triaged. | J85: Fintepla, Firdapse
A86: Intake: Pending Ins Coverage | B86: 3. Order Entry / Completion | C86: Intake: Pending Ins Coverage | D86: Intake: Pending Ins Coverage | F86: Pending | G86: Utilize when patient insurance is effective on a specific future date | J86: All
A87: Intake: Pending Override | B87: 3. Order Entry / Completion | C87: Intake: Pending Payer Override | D87: Intake-Pending Override | F87: Pending | G87: Utilize when waiting on override for cost, LDD, etc., from payer | J87: All
A88: Intake: Pending PAP Documents | B88: 3. Order Entry / Completion | C88: Intake: Pending PAP Documents | D88: Intake: Pending PAP Documents | F88: Pending | G88: Utilize when PAP documents have been sent to patient
A89: Intake: Pending Phys add | B89: 3. Order Entry / Completion | C89: Intake: BV In Process | D89: Intake: BV In Process | F89: Pending | G89: Utilize when HCP has to be added to system | J89: All
A90: Intake: Pending Phys- Alt Therapy Decision | B90: 3. Order Entry / Completion | C90: Intake: Pending Phys- Alt Therapy Decision | D90: Intake: Pending Phys- Alt Therapy Decision | F90: Pending | G90: Utilize when waiting for HCP to determine if he will change therapies | J90: All
A91: Intake: Pending Phys- PA Decision | B91: 3. Order Entry / Completion | C91: Intake: Pending Phys- PA Decision | D91: Intake: Pending Phys- PA Decision | F91: Pending | G91: Utilize when waiting for HCP to decide if he will submit PA | J91: All
A92: Intake: Pending Phys-Appeal Decision | B92: 3. Order Entry / Completion | C92: Intake: Pending Phys-Appeal Decision | D92: Intake: Pending Phys-Appeal Decision | F92: Pending | G92: Utilize when waiting for HCP to decide if he will submit Appeal | J92: All
A93: Intake: Unreachable Letter Sent | B93: 3. Order Entry / Completion | C93: Intake: Unreachable letter sent | D93: Intake: Unreachable letter sent | F93: Pending | G93: Utlize when Unreachable letter is mailed | J93: All | K93: Last event date > 2 weeks - Pending Closed
A94: Intake: Waiting for VA approval | B94: 3. Order Entry / Completion | C94: Intake: Waiting for VA approval | D94: Intake: Waiting for VA approval | F94: Pending | G94: Utilize when waiting on payment or PO from VA | J94: All
A95: Intake: Waiting for VA approval | B95: 3. Order Entry / Completion | C95: Waiting for Approval VA | D95: Waiting for Approval VA | F95: Pending
A96: Maintenance Dose Rx | B96: 4. Rx Setup | C96: Rx Clarification Needed | D96: Maintenance Dose Rx | F96: Pending | G96: Utilize if patient has a titration Rx that needs to be set up; waiting on fill date to set up maintenance dose Rx | J96: All | K96: use last event from other open order
A97: MD/patient notified- Attempt 1 | B97: I. Rx Expiration / Zero Refills | C97: New Rx Needed- Call to MD/ Patient- attempt 1 | D97: New Rx Needed- Call to MD/ Patient- attempt 1 | F97: Active | G97: Utilize Day 7 if attempt is made to contact MD and patient for new Rx | H97: X | J97: All
A98: MD/patient notified- Attempt 2 | B98: I. Rx Expiration / Zero Refills | C98: New Rx Needed- Call to MD/ Patient- attempt 2 | D98: New Rx Needed- Call to MD/ Patient- attempt 2 | F98: Active
A99: New RX received | B99: 4. Rx Setup | C99: Rx Verification | D99: New Rx Received | F99: Pending | G99: Utilize if clarification received with new Rx
A100: New RX received | B100: B. Patients to Contact - Refills | C100: New Rx Received | D100: New Rx Received | F100: Active | G100: Utilize when New prescription received in SP but not reviewed yet by pharmacist | J100: All
...

Sheet Sheet2
A1: pk | B1: poptext
A2: 1027 | B2: 1st eRx Attempt | C2: =VLOOKUP(B2,'Order Last Event Mapping'!A:A,1,FALSE) -> 1st eRx Attempt
A3: 793 | B3: 1st Fax Attempt | C3: =VLOOKUP(B3,'Order Last Event Mapping'!A:A,1,FALSE) -> 1st Fax Attempt
A4: 786 | B4: 1st Scheduling Attempt | C4: =VLOOKUP(B4,'Order Last Event Mapping'!A:A,1,FALSE) -> 1st Scheduling Attempt
A5: 1068 | B5: 2nd eRx Attempt | C5: =VLOOKUP(B5,'Order Last Event Mapping'!A:A,1,FALSE) -> 2nd eRx Attempt
A6: 794 | B6: 2nd Fax Attempt | C6: =VLOOKUP(B6,'Order Last Event Mapping'!A:A,1,FALSE) -> 2nd Fax Attempt
A7: 787 | B7: 2nd Scheduling Attempt | C7: =VLOOKUP(B7,'Order Last Event Mapping'!A:A,1,FALSE) -> 2nd Scheduling Attempt
A8: 788 | B8: 3rd Scheduling Attempt | C8: =VLOOKUP(B8,'Order Last Event Mapping'!A:A,1,FALSE) -> 3rd Scheduling Attempt
A9: 791 | B9: 4th Scheduling Attempt | C9: =VLOOKUP(B9,'Order Last Event Mapping'!A:A,1,FALSE) -> 4th Scheduling Attempt
A10: 1069 | B10: 5th Scheduling Attempt | C10: =VLOOKUP(B10,'Order Last Event Mapping'!A:A,1,FALSE) -> 5th Scheduling Attempt
A11: 1070 | B11: 6th Scheduling Attempt | C11: =VLOOKUP(B11,'Order Last Event Mapping'!A:A,1,FALSE) -> 6th Scheduling Attempt
A12: 683 | B12: Add Prescriber to Order | C12: =VLOOKUP(B12,'Order Last Event Mapping'!A:A,1,FALSE) -> #N/A
A13: 1021 | B13: Alkindi Pharmacist review needed | C13: =VLOOKUP(B13,'Order Last Event Mapping'!A:A,1,FALSE) -> #N/A
... A320: 909 | B320: ZZZWS - Returned for Correction | C320: =VLOOKUP(B320,'Order Last Event Mapping'!A:A,1,FALSE) -> #N/A
